lynceus/__init__.py
lynceus/core/__init__.py
lynceus/core/config/__init__.py
lynceus/core/config/lynceus_config.py
lynceus/core/exchange/__init__.py
lynceus/core/exchange/lynceus_exchange.py
lynceus/core/logger_utils.py
lynceus/core/lynceus.py
lynceus/core/lynceus_client.py
lynceus/core/lynceus_message_status.py
lynceus/devops/__init__.py
lynceus/devops/devops_analyzer.py
lynceus/devops/editor/__init__.py
lynceus/devops/editor/devops_analyzer_editor.py
lynceus/devops/editor/github_devops_analyzer_editor.py
lynceus/devops/editor/gitlab_devops_analyzer_editor.py
lynceus/devops/factory.py
lynceus/devops/github_devops_analyzer.py
lynceus/devops/gitlab_devops_analyzer.py
lynceus/files/__init__.py
lynceus/files/file_factory.py
lynceus/files/lynceus_file.py
lynceus/files/remote/__init__.py
lynceus/files/remote/s3.py
lynceus/files/storage.py
lynceus/lynceus_exceptions.py
lynceus/misc/lynceus.default.conf
lynceus/utils/__init__.py
lynceus/utils/lynceus_dict.py
lynceus/utils/randomizer.py
lynceus/utils/storage.py
lynceus-2.0.1.dist-info/LICENSE
lynceus-2.0.1.dist-info/METADATA
lynceus-2.0.1.dist-info/WHEEL
lynceus-2.0.1.dist-info/RECORD
