Metadata-Version: 2.3
Name: lynceus
Version: 2.0.1
Summary: Lynceus is a sophisticated and resilient Python toolbox designed to serve as the foundational core layer of your Python applications. It offers features like configuration file management with inheritance and automatic JSON loading, seamless logger configuration, efficient session management, and unified file handling for both local and remote storage. By providing a plethora of utilities, Lynceus allows developers to skip the mundane setup and focus directly on what truly matters.
License: GPL-3.0-or-later
Author: Bertrand BENOIT
Author-email: contact@bertrand-benoit.net
Requires-Python: >=3.10.0,<4
Classifier: Development Status :: 5 - Production/Stable
Classifier: Intended Audience :: Developers
Classifier: License :: OSI Approved :: GNU General Public License v3 (GPLv3)
Classifier: License :: OSI Approved :: GNU General Public License v3 or later (GPLv3+)
Classifier: Natural Language :: English
Classifier: Operating System :: OS Independent
Classifier: Programming Language :: Python :: 3
Classifier: Programming Language :: Python :: 3.10
Classifier: Programming Language :: Python :: 3.11
Classifier: Programming Language :: Python :: 3.12
Classifier: Programming Language :: Python :: 3.13
Classifier: Topic :: Software Development :: Libraries :: Python Modules
Classifier: Topic :: Utilities
Requires-Dist: PyGithub (>=2.1,<3.0)
Requires-Dist: fsspec (>=2025.7,<2026.0)
Requires-Dist: pandas (>=2.2,<3.0)
Requires-Dist: pandas-stubs (>=2.2,<3.0)
Requires-Dist: pyarrow (>=21.0,<22.0)
Requires-Dist: pytest-mock (>=3.14.1,<4.0.0)
Requires-Dist: python-gitlab (>=6.2,<7.0)
Requires-Dist: s3fs[boto3] (>=2025.7,<2026.0)
Requires-Dist: setuptools (>=80.9,<81)
Project-URL: Bug Tracker, https://gitlab.com/bertrand-benoit/lynceus/-/issues
